Workbook

Sheet Dashboard
A1: SAMPLE ACCOUNTING & BOOKKEEPING PORTFOLIO
A3: All figures and counterparties in this workbook are fictional and for demonstration only.
A5: Metric | B5: Sample Value | C5: Interpretation
A6: Total invoiced sales | B6: =SUM(Sales!E:E) | C6: Total value of issued invoices
A7: Total collections | B7: =SUM(Collections!E:E) | C7: Receipts recorded against invoices
A8: Total expenses | B8: =SUM(Expenses!F:F) | C8: Operating and cost-of-sales expenses
A9: Outstanding receivables | B9: =SUM(Receivables!G:G) | C9: Invoice balance less recorded receipts
A10: Net profit before tax | B10: ='Profit & Loss'!E6 | C10: Sales less all expenses
A13: Portfolio skills demonstrated
A14: • Accounts receivable tracking and aging
A15: • Cash receipt recording and invoice matching
A16: • Expense categorization and spend review
A17: • Monthly profit-and-loss reporting
A18: • Basic data validation and audit trail awareness

Sheet Sales
A1: SALES — FICTIONAL SAMPLE DATA
A2: Date | B2: Invoice_Ref | C2: Customer | D2: Salesperson | E2: Invoice_Amount | F2: Payment_Type | G2: Month | H2: Month
A3: 46027 | B3: INV-1001 | C3: Northstar Retail | D3: Sales Rep A | E3: 1250 | F3: Credit | G3: 2026-01 | H3: =TEXT(A3,"yyyy-mm")
A4: 46030 | B4: INV-1002 | C4: Maple Corner Shop | D4: Sales Rep B | E4: 890 | F4: Bank Transfer | G4: 2026-01 | H4: =TEXT(A4,"yyyy-mm")
A5: 46036 | B5: INV-1003 | C5: Harbor Market | D5: Sales Rep A | E5: 1640 | F5: Credit | G5: 2026-01 | H5: =TEXT(A5,"yyyy-mm")
A6: 46055 | B6: INV-1004 | C6: Cedar & Co. | D6: Sales Rep C | E6: 1120 | F6: Card | G6: 2026-02 | H6: =TEXT(A6,"yyyy-mm")
A7: 46063 | B7: INV-1005 | C7: Brightway Stores | D7: Sales Rep B | E7: 2150 | F7: Credit | G7: 2026-02 | H7: =TEXT(A7,"yyyy-mm")
A8: 46071 | B8: INV-1006 | C8: Northstar Retail | D8: Sales Rep A | E8: 760 | F8: Cash | G8: 2026-02 | H8: =TEXT(A8,"yyyy-mm")
A9: 46084 | B9: INV-1007 | C9: Maple Corner Shop | D9: Sales Rep C | E9: 1390 | F9: Credit | G9: 2026-03 | H9: =TEXT(A9,"yyyy-mm")
A10: 46093 | B10: INV-1008 | C10: Harbor Market | D10: Sales Rep B | E10: 980 | F10: Bank Transfer | G10: 2026-03 | H10: =TEXT(A10,"yyyy-mm")
A11: 46101 | B11: INV-1009 | C11: Cedar & Co. | D11: Sales Rep A | E11: 1875 | F11: Credit | G11: 2026-03 | H11: =TEXT(A11,"yyyy-mm")

Sheet Collections
A1: COLLECTIONS — FICTIONAL SAMPLE DATA
A2: Receipt_Date | B2: Receipt_Ref | C2: Invoice_Ref | D2: Customer | E2: Amount | F2: Payment_Method | G2: Month
A3: 46032 | B3: RCPT-2001 | C3: INV-1001 | D3: Northstar Retail | E3: 500 | F3: Bank Transfer | G3: 2026-01
A4: 46038 | B4: RCPT-2002 | C4: INV-1002 | D4: Maple Corner Shop | E4: 890 | F4: Bank Transfer | G4: 2026-01
A5: 46047 | B5: RCPT-2003 | C5: INV-1003 | D5: Harbor Market | E5: 400 | F5: Cash | G5: 2026-01
A6: 46058 | B6: RCPT-2004 | C6: INV-1004 | D6: Cedar & Co. | E6: 1120 | F6: Card | G6: 2026-02
A7: 46069 | B7: RCPT-2005 | C7: INV-1005 | D7: Brightway Stores | E7: 1000 | F7: Bank Transfer | G7: 2026-02
A8: 46075 | B8: RCPT-2006 | C8: INV-1001 | D8: Northstar Retail | E8: 300 | F8: Bank Transfer | G8: 2026-02
A9: 46091 | B9: RCPT-2007 | C9: INV-1007 | D9: Maple Corner Shop | E9: 700 | F9: Bank Transfer | G9: 2026-03
A10: 46096 | B10: RCPT-2008 | C10: INV-1008 | D10: Harbor Market | E10: 980 | F10: Bank Transfer | G10: 2026-03
A11: 46106 | B11: RCPT-2009 | C11: INV-1009 | D11: Cedar & Co. | E11: 500 | F11: Cash | G11: 2026-03

Sheet Expenses
A1: EXPENSES — FICTIONAL SAMPLE DATA
A2: Date | B2: Expense_Ref | C2: Category | D2: Vendor | E2: Description | F2: Amount | G2: Payment_Method | H2: Month | I2: Month
A3: 46028 | B3: EXP-3001 | C3: Rent | D3: Sample Property Ltd | E3: Office rent | F3: 650 | G3: Bank Transfer | H3: 2026-01 | I3: =TEXT(A3,"yyyy-mm")
A4: 46031 | B4: EXP-3002 | C4: Utilities | D4: Utility Services | E4: Electricity and water | F4: 115 | G4: Bank Transfer | H4: 2026-01 | I4: =TEXT(A4,"yyyy-mm")
A5: 46037 | B5: EXP-3003 | C5: Cost of Sales | D5: Sample Supplier | E5: Inventory purchase | F5: 720 | G5: Bank Transfer | H5: 2026-01 | I5: =TEXT(A5,"yyyy-mm")
A6: 46057 | B6: EXP-3004 | C6: Transport | D6: City Logistics | E6: Delivery costs | F6: 145 | G6: Card | H6: 2026-02 | I6: =TEXT(A6,"yyyy-mm")
A7: 46064 | B7: EXP-3005 | C7: Salaries | D7: Payroll Services | E7: Monthly payroll | F7: 950 | G7: Bank Transfer | H7: 2026-02 | I7: =TEXT(A7,"yyyy-mm")
A8: 46072 | B8: EXP-3006 | C8: Cost of Sales | D8: Sample Supplier | E8: Inventory purchase | F8: 880 | G8: Bank Transfer | H8: 2026-02 | I8: =TEXT(A8,"yyyy-mm")
A9: 46086 | B9: EXP-3007 | C9: Utilities | D9: Utility Services | E9: Internet and utilities | F9: 130 | G9: Bank Transfer | H9: 2026-03 | I9: =TEXT(A9,"yyyy-mm")
A10: 46094 | B10: EXP-3008 | C10: Office | D10: Office Supplies Co. | E10: Stationery | F10: 85 | G10: Card | H10: 2026-03 | I10: =TEXT(A10,"yyyy-mm")
A11: 46102 | B11: EXP-3009 | C11: Cost of Sales | D11: Sample Supplier | E11: Inventory purchase | F11: 1020 | G11: Bank Transfer | H11: 2026-03 | I11: =TEXT(A11,"yyyy-mm")

Sheet Receivables
A1: ACCOUNTS RECEIVABLES & AGING
A2: Customer | B2: Invoice_Ref | C2: Invoice_Date | D2: Due_Date | E2: Invoice_Amount | F2: Collections | G2: Outstanding
A3: Northstar Retail | B3: INV-1001 | C3: 46027 | D3: 46057 | E3: 1250 | F3: =SUMIF(Collections!C:C,B3,Collections!E:E) | G3: =MAX(0,E3-F3)
A4: Maple Corner Shop | B4: INV-1002 | C4: 46030 | D4: 46060 | E4: 890 | F4: =SUMIF(Collections!C:C,B4,Collections!E:E) | G4: =MAX(0,E4-F4)
A5: Harbor Market | B5: INV-1003 | C5: 46036 | D5: 46066 | E5: 1640 | F5: =SUMIF(Collections!C:C,B5,Collections!E:E) | G5: =MAX(0,E5-F5)
A6: Cedar & Co. | B6: INV-1004 | C6: 46055 | D6: 46085 | E6: 1120 | F6: =SUMIF(Collections!C:C,B6,Collections!E:E) | G6: =MAX(0,E6-F6)
A7: Brightway Stores | B7: INV-1005 | C7: 46063 | D7: 46093 | E7: 2150 | F7: =SUMIF(Collections!C:C,B7,Collections!E:E) | G7: =MAX(0,E7-F7)
A8: Northstar Retail | B8: INV-1006 | C8: 46071 | D8: 46101 | E8: 760 | F8: =SUMIF(Collections!C:C,B8,Collections!E:E) | G8: =MAX(0,E8-F8)
A9: Maple Corner Shop | B9: INV-1007 | C9: 46084 | D9: 46114 | E9: 1390 | F9: =SUMIF(Collections!C:C,B9,Collections!E:E) | G9: =MAX(0,E9-F9)
A10: Harbor Market | B10: INV-1008 | C10: 46093 | D10: 46123 | E10: 980 | F10: =SUMIF(Collections!C:C,B10,Collections!E:E) | G10: =MAX(0,E10-F10)
A11: Cedar & Co. | B11: INV-1009 | C11: 46101 | D11: 46131 | E11: 1875 | F11: =SUMIF(Collections!C:C,B11,Collections!E:E) | G11: =MAX(0,E11-F11)

Sheet Profit & Loss
A1: MONTHLY PROFIT & LOSS SUMMARY
A2: Month | B2: Sales Revenue | C2: Cost of Sales | D2: Operating Expenses | E2: Net Profit Before Tax | F2: Net Margin
A3: 2026-01 | B3: =SUMIFS(Sales!E:E,Sales!G:G,A3) | C3: =SUMIFS(Expenses!F:F,Expenses!H:H,A3,Expenses!C:C,"Cost of Sales") | D3: =SUMIFS(Expenses!F:F,Expenses!H:H,A3)-C3 | E3: =B3-C3-D3 | F3: =IFERROR(E3/B3,0)
A4: 2026-02 | B4: =SUMIFS(Sales!E:E,Sales!G:G,A4) | C4: =SUMIFS(Expenses!F:F,Expenses!H:H,A4,Expenses!C:C,"Cost of Sales") | D4: =SUMIFS(Expenses!F:F,Expenses!H:H,A4)-C4 | E4: =B4-C4-D4 | F4: =IFERROR(E4/B4,0)
A5: 2026-03 | B5: =SUMIFS(Sales!E:E,Sales!G:G,A5) | C5: =SUMIFS(Expenses!F:F,Expenses!H:H,A5,Expenses!C:C,"Cost of Sales") | D5: =SUMIFS(Expenses!F:F,Expenses!H:H,A5)-C5 | E5: =B5-C5-D5 | F5: =IFERROR(E5/B5,0)
